proalgotrader_core/__init__.py
proalgotrader_core/algo_session.py
proalgotrader_core/algorithm.py
proalgotrader_core/algorithm_factory.py
proalgotrader_core/api.py
proalgotrader_core/application.py
proalgotrader_core/args_manager.py
proalgotrader_core/bar.py
proalgotrader_core/base_algorithm.py
proalgotrader_core/base_symbol.py
proalgotrader_core/broker.py
proalgotrader_core/broker_info.py
proalgotrader_core/broker_manager.py
proalgotrader_core/broker_symbol.py
proalgotrader_core/candle_processors.py
proalgotrader_core/chart.py
proalgotrader_core/chart_manager.py
proalgotrader_core/github_repository.py
proalgotrader_core/notification_manager.py
proalgotrader_core/order.py
proalgotrader_core/order_item.py
proalgotrader_core/pnl_calculator.py
proalgotrader_core/position.py
proalgotrader_core/project.py
proalgotrader_core/risk_reward.py
proalgotrader_core/risk_reward_manager.py
proalgotrader_core/start.py
proalgotrader_core/tick.py
proalgotrader_core/trade.py
proalgotrader_core/_helpers/__init__.py
proalgotrader_core/_helpers/data_validation.py
proalgotrader_core/_helpers/deprecated.py
proalgotrader_core/_helpers/get_data_path.py
proalgotrader_core/_helpers/get_strike_price.py
proalgotrader_core/_helpers/logging_config.py
proalgotrader_core/di/container.py
proalgotrader_core/enums/__init__.py
proalgotrader_core/enums/account_type.py
proalgotrader_core/enums/candle_type.py
proalgotrader_core/enums/market_type.py
proalgotrader_core/enums/order_type.py
proalgotrader_core/enums/position_manager_type.py
proalgotrader_core/enums/position_type.py
proalgotrader_core/enums/product_type.py
proalgotrader_core/enums/risk_reward_unit.py
proalgotrader_core/enums/segment_type.py
proalgotrader_core/enums/symbol_type.py
proalgotrader_core/enums/symbols/__init__.py
proalgotrader_core/enums/symbols/index_type.py
proalgotrader_core/enums/symbols/stock_type.py
proalgotrader_core/indicators/__init__.py
proalgotrader_core/indicators/indicator.py
proalgotrader_core/indicators/indicators.py
proalgotrader_core-0.5.2.dist-info/METADATA
proalgotrader_core-0.5.2.dist-info/WHEEL
proalgotrader_core-0.5.2.dist-info/top_level.txt
proalgotrader_core-0.5.2.dist-info/RECORD
