Metadata-Version: 2.4
Name: proalgotrader-core
Version: 0.5.2
Summary: ProAlgoTrader Core
Author-email: Krunal Dodiya <kunal.dodiya1@gmail.com>
License-Expression: MIT
Requires-Python: >=3.10
Requires-Dist: dependency-injector>=4.48.1
Requires-Dist: fyers-apiv3>=3.1.7
Requires-Dist: logzero>=1.7.0
Requires-Dist: norenrestapipy>=0.0.22
Requires-Dist: polars>=1.32.3
Requires-Dist: pusher>=3.3.3
Requires-Dist: python-dotenv>=1.1.1
Requires-Dist: pytz>=2025.2
Requires-Dist: requests==2.31.0
Requires-Dist: setuptools
Requires-Dist: smartapi-python>=1.5.5
Requires-Dist: streamlit>=1.41.0
Requires-Dist: tenacity>=9.1.2
